<?xml version="1.0" encoding="utf-8"?>
<!--
/*
** Copyright 2006, Google Inc.
**
** Licensed under the Apache License, Version 2.0 (the "License");
** you may not use this file except in compliance with the License.
** You may obtain a copy of the License at
**
**     http://www.apache.org/licenses/LICENSE-2.0
**
** Unless required by applicable law or agreed to in writing, software
** distributed under the License is distributed on an "AS IS" BASIS,
** WITHOUT WARRANTIES OR CONDITIONS OF ANY KIND, either express or implied.
** See the License for the specific language governing permissions and
** limitations under the License.
*/
-->

<!-- use empty string to specify no proxy or port -->
<!-- This version must agree with that in apps/common/res/apns.xml -->
<apns version="8">
	<apn carrier="中国电信WAP设置CTWAP" 
		mcc="460"  
		mnc="03" 
		apn="ctwap" 
		user="ctwap@mycdma.cn" 
		password="vnet.mobi" 
		mmsc="" 
		proxy="" 
		port="" 
		mmsproxy=""  
		mmsport="" 
		authtype="3" 
		type="default,supl"
	/>
	
	<apn carrier="中国电信互联网设置CTNET"
         mcc="460"
         mnc="03"
         apn="ctnet"
         proxy=""
         port=""
         mmsproxy=""
         mmsport=""
         mmsc=""
         server=""
         user="ctnet@mycdma.cn"
         password="vnet.mobi"
         authtype="3"
         type="default,hipri,dun,fota,supl"
    />
<!--ZTE:liushaohua added for china telecom mms -->
	<apn carrier="中国电信彩信设置" 
		mcc="460"  
		mnc="03" 
		apn="ctwap" 
		user="ctwap@mycdma.cn" 
		password="vnet.mobi" 
		mmsc="http://mmsc.vnet.mobi" 
		proxy="10.0.0.200" 
		port="80" 
		mmsproxy="10.0.0.200"  
		mmsport="80" 
		authtype="3" 
		type="mms"
	/>
<!--ZTE:liushaohua added for china telecom mms -->	
<!--ZTE:liushaohua added for support china telecom 4G usim card -->
	<apn carrier="中国电信WAP设置CTWAP" 
		mcc="460"
		mnc="11"
		apn="ctwap"
		user="ctwap@mycdma.cn"
		password="vnet.mobi" 
		mmsc=""
		proxy=""
		port="" 
		mmsproxy=""
		mmsport=""
		authtype="3"
		type="default,supl"
	/>
	
<apn carrier="中国电信互联网设置CTNET"
         mcc="460"
		 mnc="11"
		 apn="ctnet"
		 proxy=""
		 port=""
		 mmsproxy=""
		 mmsport=""
		 mmsc=""
		 server=""
		 user="ctnet@mycdma.cn"
		 password="vnet.mobi"
		 authtype="3"
		 type="default,hipri,dun,fota,supl"
    />
<!--ZTE:liushaohua added for china telecom mms -->
	<apn carrier="中国电信彩信设置" 
		mcc="460"
		mnc="11"
		apn="ctwap"
		user="ctwap@mycdma.cn"
		password="vnet.mobi" 
		mmsc="http://mmsc.vnet.mobi"
		proxy="10.0.0.200"
		port="80" 
		mmsproxy="10.0.0.200"
		mmsport="80"
		authtype="3"
		type="mms"
	/>
<!--ZTE:liushaohua added for china telecom mms -->
<!--ZTE:liushaohua added for support china telecom 4G usim card -->

	<apn carrier="中国电信WAP设置CTWAP" 
		mcc="460"  
		mnc="99" 
		apn="ctwap" 
		user="ctwap@mycdma.cn" 
		password="vnet.mobi" 
		mmsc="" 
		proxy="" 
		port="" 
		mmsproxy=""  
		mmsport="" 
		authtype="3" 
		type="default,supl"
	/>
	
	<apn carrier="中国电信互联网设置CTNET"
         mcc="460"
         mnc="99"
         apn="ctnet"
         proxy=""
         port=""
         mmsproxy=""
         mmsport=""
         mmsc=""
         server=""
         user="ctnet@mycdma.cn"
         password="vnet.mobi"
         authtype="3"
         type="default,hipri,dun,fota,supl"
    />
	<apn carrier="中国电信彩信设置" 
		mcc="460"  
		mnc="99" 
		apn="ctwap" 
		user="ctwap@mycdma.cn" 
		password="vnet.mobi" 
		mmsc="http://mmsc.vnet.mobi" 
		proxy="10.0.0.200" 
		port="80" 
		mmsproxy="10.0.0.200"  
		mmsport="80" 
		authtype="3" 
		type="mms"
	/>
	<apn carrier="中国电信WAP设置CTWAP" 
		mcc="204"  
		mnc="04" 
		apn="ctwap" 
		user="ctwap@mycdma.cn" 
		password="vnet.mobi" 
		mmsc="" 
		proxy="" 
		port="" 
		mmsproxy=""  
		mmsport="" 
		authtype="3" 
		type="default,supl"
	/>
	
	<apn carrier="中国电信互联网设置CTNET" 
		mcc="204" mnc="04" 
		apn="ctnet" 
		user="ctnet@mycdma.cn" 
		password="vnet.mobi" 
		authtype="3" 
		type="default,dun,fota,hipri,supl"
	/>
	
	<apn carrier="中国电信彩信设置" 
		mcc="204"  
		mnc="04" 
		apn="ctwap" 
		user="ctwap@mycdma.cn" 
		password="vnet.mobi" 
		mmsc="http://mmsc.vnet.mobi" 
		proxy="10.0.0.200" 
		port="80" 
		mmsproxy="10.0.0.200"  
		mmsport="80" 
		authtype="3" 
		type="mms"
	/>	
	
	<apn carrier="中国电信WAP设置CTWAP" 
		mcc="454"  
		mnc="04" 
		apn="ctwap" 
		user="ctwap@mycdma.cn" 
		password="vnet.mobi" 
		mmsc="" 
		proxy="" 
		port="" 
		mmsproxy=""  
		mmsport="" 
		authtype="3" 
		type="default,supl"
	/>	
	
	<apn carrier="中国电信互联网设置CTNET" 
		mcc="454" 
		mnc="04" 
		apn="ctnet" 
		user="ctnet@mycdma.cn" 
		password="vnet.mobi" 
		authtype="3" 
		type="default,dun,fota,supl"
	/>
	
	<apn carrier="中国电信彩信设置" 
		mcc="454"  
		mnc="04" 
		apn="ctwap" 
		user="ctwap@mycdma.cn" 
		password="vnet.mobi" 
		mmsc="http://mmsc.vnet.mobi" 
		proxy="10.0.0.200" 
		port="80" 
		mmsproxy="10.0.0.200"  
		mmsport="80" 
		authtype="3" 
		type="mms"
	/>
	
	<apn carrier="中国电信WAP设置CTWAP" 
		mcc="455"  
		mnc="05" 
		apn="ctwap" 
		user="ctwap@mycdma.cn" 
		password="vnet.mobi" 
		mmsc="" 
		proxy="" 
		port="" 
		mmsproxy=""  
		mmsport="" 
		authtype="3" 
		type="default,supl"
	/>	
  
	<apn carrier="中国电信互联网设置CTNET" 
		mcc="455" 
		mnc="05" 
		apn="ctnet" 
		user="ctnet@mycdma.cn" 
		password="vnet.mobi" 
		authtype="3" 
		type="default,dun,fota,supl"
	/>

	<apn carrier="中国电信彩信设置" 
		mcc="455"  
		mnc="05" 
		apn="ctwap" 
		user="ctwap@mycdma.cn" 
		password="vnet.mobi" 
		mmsc="http://mmsc.vnet.mobi" 
		proxy="10.0.0.200" 
		port="80" 
		mmsproxy="10.0.0.200"  
		mmsport="80" 
		authtype="3" 
		type="mms"
	/>		

   <apn carrier="沃3G连接互联网"
         mcc="460"
         mnc="01"
         apn="3gnet"
         proxy=""
         port=""
         mmsc=""
         mmsproxy=""
         mmsport=""
         server=""
         user=""
         password=""
         authtype="3"
         type="default,supl"
    />    
    <apn carrier="沃3G手机上网"
         mcc="460"
         mnc="01"
         apn="3gwap"
         proxy="10.0.0.172"
         port="80"
         mmsc=""
         mmsproxy=""
         mmsport=""
         server=""
         user=""
         password=""
         authtype="3"
         type="default"
    /> 
    <apn carrier="联通彩信"
         mcc="460"
         mnc="01"
         apn="3gwap"
         proxy=""
         port=""
         mmsc="http://mmsc.myuni.com.cn"
         mmsproxy="10.0.0.172"
         mmsport="80"
         server=""
         user=""
         password=""
         authtype="3"
         type="mms"
    /> 
    <apn carrier="中国移动因特网设置"
         mcc="460"
         mnc="00"
         apn="cmnet"
         proxy=""
         port=""
         mmsproxy=""
         mmsport=""
         mmsc=""
         server=""
         user=""
         password=""
         authtype="3"
         type="default,supl"
    />
    <apn carrier="中国移动WAP设置"
         mcc="460"
         mnc="00"
         apn="cmwap"
         proxy="10.0.0.172"
         port="80"
         mmsproxy=""
         mmsport=""
         mmsc=""
         server=""
         user=""
         password=""
         authtype="3"
         type="default,supl"
    />
    <apn carrier="中国移动彩信设置"
         mcc="460"
         mnc="00"
         apn="cmwap"
         proxy=""
         port=""
         mmsproxy="10.0.0.172"
         mmsport="80"
         mmsc="http://mmsc.monternet.com"
         server=""
         user=""
         password=""
         authtype="3"
         type="mms"
    />
    <apn carrier="中国移动因特网设置"
         mcc="460"
         mnc="02"
         apn="cmnet"
         proxy=""
         port=""
         mmsproxy=""
         mmsport=""
         mmsc=""
         server=""
         user=""
         password=""
         authtype="3"
         type="default,supl"
    />
    <apn carrier="中国移动WAP设置"
         mcc="460"
         mnc="02"
         apn="cmwap"
         proxy="10.0.0.172"
         port="80"
         mmsproxy=""
         mmsport=""
         mmsc=""
         server=""
         user=""
         password=""
         authtype="3"
         type="default,supl"
    />
    <apn carrier="中国移动彩信设置"
         mcc="460"
         mnc="02"
         apn="cmwap"
         proxy=""
         port=""
         mmsproxy="10.0.0.172"
         mmsport="80"
         mmsc="http://mmsc.monternet.com"
         server=""
         user=""
         password=""
         authtype="3"
         type="mms"
    />
     <apn carrier="中国移动因特网设置"
         mcc="460"
         mnc="07"
         apn="cmnet"
         proxy=""
         port=""
         mmsproxy=""
         mmsport=""
         mmsc=""
         server=""
         user=""
         password=""
         authtype="3"
         type="default,supl"
    />
    <apn carrier="中国移动WAP设置"
         mcc="460"
         mnc="07"
         apn="cmwap"
         proxy="10.0.0.172"
         port="80"
         mmsproxy=""
         mmsport=""
         mmsc=""
         server=""
         user=""
         password=""
         authtype="3"
         type="default,supl"
    />
    <apn carrier="中国移动彩信设置"
         mcc="460"
         mnc="07"
         apn="cmwap"
         proxy=""
         port=""
         mmsproxy="10.0.0.172"
         mmsport="80"
         mmsc="http://mmsc.monternet.com"
         server=""
         user=""
         password=""
         authtype="3"
         type="mms"
    />
</apns>
